{"complaint": "M338597", "accident": "35886/2020", "brand": "suzuki", "model": "n4palto maruti", "type": "auto", "color": "gris", "damage_comment": "paragolpe delantero, guardabarro delantero derecho,  optica delantera derecha y demas a corroborar", "car_year": 2018, "damaged_parts": [{"part": "farol_delantero_derecho", "part_text": "Farol Delantero Derecho", "task": "repair", "hours": 0}, {"part": "paragolpe_delantero", "part_text": "Paragolpe Delantero", "task": "repair", "hours": 0}, {"part": "guardabarro_delantero_derecho", "part_text": "Guardabarro Delantero Derecho", "task": "repair", "hours": 0}, {"part": "farol_delantero_izquierdo", "part_text": "Farol Delantero Izquierdo", "task": "repair", "hours": 0}]}