{"complaint": "M350529", "accident": "6723/2021", "brand": "volkswagen", "model": "n4pup nuevo hig", "type": "auto", "color": "rojo", "damage_comment": "p.golpe y panel trasero tapa y piso baul farol guardabarro y puerta trasera izquierda conf. int baul rueda trasera izquierda", "car_year": 2021, "damaged_parts": [{"part": "paragolpe_trasero", "part_text": "Paragolpe Trasero", "task": "repair", "hours": 0}, {"part": "guardabarro_trasero_izquierdo", "part_text": "Guardabarro Trasero Izquierdo", "task": "repair", "hours": 0}, {"part": "farol_trasero_izquierdo", "part_text": "Farol Trasero Izquierdo", "task": "repair", "hours": 0}, {"part": "panel_trasero", "part_text": "Panel Trasero", "task": "repair", "hours": 0}, {"part": "techo", "part_text": "Techo", "task": "repair", "hours": 0}, {"part": "tapa_de_baul", "part_text": "Tapa de Baul", "task": "repair", "hours": 0}, {"part": "puerta_trasera_izquierda", "part_text": "Puerta Trasera Izquierda", "task": "repair", "hours": 0}]}