{"complaint": "M357278", "accident": "15893/2021", "brand": "peugeot", "model": "n2ppartner 1.6", "type": "auto", "color": "gris", "damage_comment": "ambas puertas de furgon,defensa trasera, paragolpe trasero.", "car_year": 2017, "damaged_parts": [{"part": "paragolpe_trasero", "part_text": "Paragolpe Trasero", "task": "repair", "hours": 0}, {"part": "tapa_de_baul", "part_text": "Tapa de Baul", "task": "repair", "hours": 0}, {"part": "tapa_de_baul", "part_text": "Tapa de Baul", "task": "repair", "hours": 0}]}