{"complaint": "M363267", "accident": "20702/2021", "brand": "volkswagen", "model": "n4pgol vii 1.6", "type": "auto", "color": "gris", "damage_comment": "puerta trasera derecha,  guardabarro trasero derecho, paragolpe trasero y demas a corroborar", "car_year": 2018, "damaged_parts": [{"part": "paragolpe_trasero", "part_text": "Paragolpe Trasero", "task": "repair", "hours": 0}, {"part": "guardabarro_trasero_derecho", "part_text": "Guardabarro Trasero Derecho", "task": "repair", "hours": 0}, {"part": "zocalo_derecho", "part_text": "Zocalo Derecho", "task": "repair", "hours": 0}, {"part": "farol_trasero_derecho", "part_text": "Farol Trasero Derecho", "task": "repair", "hours": 0}, {"part": "farol_trasero_izquierdo", "part_text": "Farol Trasero Izquierdo", "task": "repair", "hours": 0}, {"part": "puerta_trasera_derecha", "part_text": "Puerta Trasera Derecha", "task": "repair", "hours": 0}]}