{"complaint": "M361011", "accident": "17308/2021", "brand": "chevrolet", "model": "nonix 1.0 ls a/", "type": "auto", "color": "gris", "damage_comment": "optico del dere, guarda  buche del derecho, paragolpe del, a corroborar int y mec", "car_year": 2017, "damaged_parts": [{"part": "capot", "part_text": "Capot", "task": "repair", "hours": 0}, {"part": "paragolpe_delantero", "part_text": "Paragolpe Delantero", "task": "repair", "hours": 0}, {"part": "guardabarro_delantero_derecho", "part_text": "Guardabarro Delantero Derecho", "task": "repair", "hours": 0}, {"part": "farol_delantero_derecho", "part_text": "Farol Delantero Derecho", "task": "repair", "hours": 0}, {"part": "puerta_delantera_derecha", "part_text": "Puerta Delantera Derecha", "task": "repair", "hours": 0}, {"part": "farol_delantero_izquierdo", "part_text": "Farol Delantero Izquierdo", "task": "repair", "hours": 0}]}