{"complaint": "M357135", "accident": "13788/2021", "brand": "renault", "model": "n4pkwid 1.0 out", "type": "auto", "color": "marfil", "damage_comment": "rueda delantera derecha.paragolpe delantero,guardabarro delantero derecho.farol delantero derecho.eje delantero derecho.careta.demas a corroborar", "car_year": 2021, "damaged_parts": [{"part": "paragolpe_delantero", "part_text": "Paragolpe Delantero", "task": "repair", "hours": 0}, {"part": "farol_delantero_derecho", "part_text": "Farol Delantero Derecho", "task": "repair", "hours": 0}, {"part": "guardabarro_delantero_derecho", "part_text": "Guardabarro Delantero Derecho", "task": "repair", "hours": 0}, {"part": "farol_delantero_izquierdo", "part_text": "Farol Delantero Izquierdo", "task": "repair", "hours": 0}]}