{"complaint": "M344006", "accident": "39079/2020", "brand": "renault", "model": "n4pkwid 1.0 lif", "type": "auto", "color": "gris", "damage_comment": "ambas puertas izquierdas, paragolpe trasero, guardabarro trasero izquierdo, moldura de guardabarro trasero izquierdo, tasa y rueda trasera izquierda.", "car_year": 2021, "damaged_parts": [{"part": "guardabarro_trasero_izquierdo", "part_text": "Guardabarro Trasero Izquierdo", "task": "repair", "hours": 0}, {"part": "puerta_delantera_izquierda", "part_text": "Puerta Delantera Izquierda", "task": "repair", "hours": 0}, {"part": "puerta_trasera_izquierda", "part_text": "Puerta Trasera Izquierda", "task": "repair", "hours": 0}, {"part": "paragolpe_trasero", "part_text": "Paragolpe Trasero", "task": "repair", "hours": 0}]}