{"complaint": "M349754", "accident": "15260/2021", "brand": "cheverolet", "model": "n4pjoy", "type": "auto", "color": "blanco", "damage_comment": "lateral trasero izquierdo, puerta trasera izquierda, zocalo izquierdo, rueda trasera izquierda, demas da?os a corroborar", "car_year": 2022, "damaged_parts": [{"part": "puerta_trasera_izquierda", "part_text": "Puerta Trasera Izquierda", "task": "repair", "hours": 0}, {"part": "guardabarro_trasero_izquierdo", "part_text": "Guardabarro Trasero Izquierdo", "task": "repair", "hours": 0}, {"part": "zocalo_izquierdo", "part_text": "Zocalo Izquierdo", "task": "repair", "hours": 0}, {"part": "paragolpe_trasero", "part_text": "Paragolpe Trasero", "task": "repair", "hours": 0}, {"part": "farol_trasero_izquierdo", "part_text": "Farol Trasero Izquierdo", "task": "repair", "hours": 0}, {"part": "puerta_delantera_izquierda", "part_text": "Puerta Delantera Izquierda", "task": "repair", "hours": 0}, {"part": "zocalo_izquierdo", "part_text": "Zocalo Izquierdo", "task": "repair", "hours": 0}]}