{"complaint": "M332965", "accident": "28257/2020", "brand": "chevrolet", "model": "d4ps10 2.8 tdi", "type": "camioneta", "color": "gris", "damage_comment": "puertas derechas z?calos derechos montantes de puertas y montante central estribos de ambos laterales paragolpes retrovisor  derecho manijas de puertas defensa caja guardabarros derechos capot frente ?ptico derecho", "car_year": 2013, "damaged_parts": [{"part": "farol_delantero_izquierdo", "part_text": "Farol Delantero Izquierdo", "task": "repair", "hours": 0}, {"part": "farol_delantero_derecho", "part_text": "Farol Delantero Derecho", "task": "repair", "hours": 0}, {"part": "paragolpe_delantero", "part_text": "Paragolpe Delantero", "task": "repair", "hours": 0}, {"part": "guardabarro_delantero_derecho", "part_text": "Guardabarro Delantero Derecho", "task": "repair", "hours": 0}, {"part": "guardabarro_delantero_izquierdo", "part_text": "Guardabarro Delantero Izquierdo", "task": "repair", "hours": 0}, {"part": "puerta_trasera_derecha", "part_text": "Puerta Trasera Derecha", "task": "repair", "hours": 0}, {"part": "puerta_trasera_izquierda", "part_text": "Puerta Trasera Izquierda", "task": "repair", "hours": 0}, {"part": "lateral_de_caja_derecho", "part_text": "Lateral de Caja Derecho", "task": "repair", "hours": 0}, {"part": "lateral_de_caja_izquierdo", "part_text": "Lateral de Caja Izquierdo", "task": "repair", "hours": 0}, {"part": "puerta_delantera_izquierda", "part_text": "Puerta Delantera Izquierda", "task": "repair", "hours": 0}, {"part": "puerta_delantera_derecha", "part_text": "Puerta Delantera Derecha", "task": "repair", "hours": 0}, {"part": "techo", "part_text": "Techo", "task": "repair", "hours": 0}, {"part": "panel_trasero", "part_text": "Panel Trasero", "task": "repair", "hours": 0}, {"part": "farol_trasero_izquierdo", "part_text": "Farol Trasero Izquierdo", "task": "repair", "hours": 0}, {"part": "farol_trasero_derecho", "part_text": "Farol Trasero Derecho", "task": "repair", "hours": 0}, {"part": "capot", "part_text": "Capot", "task": "repair", "hours": 0}]}