{"complaint": "M351848", "accident": "7991/2021", "brand": "fiat", "model": "nuno way 1.3 3p", "type": "auto", "color": "gris", "damage_comment": "llanta y cubierta delantera izquierda, tren del. a corroborar int y mec guardabarro delantero izquierdo", "car_year": 2010, "damaged_parts": [{"part": "paragolpe_delantero", "part_text": "Paragolpe Delantero", "task": "repair", "hours": 0}, {"part": "guardabarro_delantero_izquierdo", "part_text": "Guardabarro Delantero Izquierdo", "task": "repair", "hours": 0}, {"part": "farol_delantero_derecho", "part_text": "Farol Delantero Derecho", "task": "repair", "hours": 0}, {"part": "farol_delantero_izquierdo", "part_text": "Farol Delantero Izquierdo", "task": "repair", "hours": 0}, {"part": "zocalo_izquierdo", "part_text": "Zocalo Izquierdo", "task": "repair", "hours": 0}, {"part": "puerta_delantera_izquierda", "part_text": "Puerta Delantera Izquierda", "task": "repair", "hours": 0}, {"part": "puerta_trasera_izquierda", "part_text": "Puerta Trasera Izquierda", "task": "repair", "hours": 0}, {"part": "capot", "part_text": "Capot", "task": "repair", "hours": 0}]}