{"complaint": "M360128", "accident": "16841/2021", "brand": "kia", "model": "n4ppicanto new", "type": "auto", "color": "rojo", "damage_comment": "aler?n,  tapa ba?l,  luneta trasera,  envolvente trasero,  zocalo,  otros a corroborar", "car_year": 2017, "damaged_parts": [{"part": "tapa_de_baul", "part_text": "Tapa de Baul", "task": "repair", "hours": 0}, {"part": "farol_trasero_izquierdo", "part_text": "Farol Trasero Izquierdo", "task": "repair", "hours": 0}, {"part": "farol_trasero_derecho", "part_text": "Farol Trasero Derecho", "task": "repair", "hours": 0}, {"part": "paragolpe_trasero", "part_text": "Paragolpe Trasero", "task": "repair", "hours": 0}, {"part": "panel_trasero", "part_text": "Panel Trasero", "task": "repair", "hours": 0}]}